DatabaseLib/__init__.py
DatabaseLib/library.py
DatabaseLib/version.py
DatabaseLib/base/__init__.py
DatabaseLib/base/robotlibcore.py
robotframework_databaselib-0.2.1.dist-info/DESCRIPTION.rst
robotframework_databaselib-0.2.1.dist-info/METADATA
robotframework_databaselib-0.2.1.dist-info/RECORD
robotframework_databaselib-0.2.1.dist-info/WHEEL
robotframework_databaselib-0.2.1.dist-info/metadata.json
robotframework_databaselib-0.2.1.dist-info/top_level.txt
